env_manager/__init__.py
env_manager/env_var_manager.py
PythonEnvVarManager-0.2.1.dist-info/LICENSE
PythonEnvVarManager-0.2.1.dist-info/METADATA
PythonEnvVarManager-0.2.1.dist-info/WHEEL
PythonEnvVarManager-0.2.1.dist-info/top_level.txt
PythonEnvVarManager-0.2.1.dist-info/RECORD
