Metadata-Version: 2.2
Name: PythonEnvVarManager
Version: 0.2.1
Summary: A simple manager to handle env variables
Author-email: Lukas <lukas@passeride.com>
Maintainer-email: Lukas <lukas@passeride.com>
License:                     GNU GENERAL PUBLIC LICENSE
Project-URL: Homepage, https://pypi.org/project/PythonEnvVarManager/
Project-URL: Documentation, https://github.com/passeride/PythonEnvVarManager
Project-URL: Repository, https://github.com/passeride/PythonEnvVarManager
Project-URL: Issues, https://github.com/passeride/PythonEnvVarManager/issues
Keywords: EnvVar,Os,Python
Requires-Python: >=3.10
License-File: LICENSE
Requires-Dist: ruff>=0.1
Requires-Dist: loguru>=0.7
Requires-Dist: python-dotenv
Provides-Extra: dev
Requires-Dist: buildtools==1.0.6; extra == "dev"
Requires-Dist: build; extra == "dev"
Requires-Dist: pytest; extra == "dev"
Requires-Dist: bumpver; extra == "dev"
Requires-Dist: twine; extra == "dev"
